{
  "results": [
    {
      "program_number": "11.021",
      "program_title": "NOAA Small Business Innovation Research (SBIR) Program",
      "popular_name": "NOAA SBIR Program"
    },
    {
      "program_number": "11.420",
      "program_title": "Coastal Zone Management Estuarine Research Reserves",
      "popular_name": ""
    },
    {
      "program_number": "11.427",
      "program_title": "Fisheries Promotion, Marketing and Development",
      "popular_name": "The Saltonstall-Kennedy Research Grant Program"
    },
    {
      "program_number": "11.468",
      "program_title": "Applied Meteorological Research",
      "popular_name": "CSTAR Program"
    },
    {
      "program_number": "11.478",
      "program_title": "Center for Sponsored Coastal Ocean Research Coastal Ocean Program",
      "popular_name": "(CRP/NCCOS)"
    }
  ]
}